[{
    "id": "Pegasus",
    "label": "Pegasus (Pegasuspy 1.3, Python 3.7.9, harmony-pytorch 0.1.6)",
    "version": "1.3",
    "updated": "2021-02-02",
    "packages": "https://raw.githubusercontent.com/klarman-cell-observatory/cumulus/master/docker/pegasus-terra/1.3/pegasus-terra-1.3-versions.json",
    "image": "cumulusprod/pegasus-terra:1.3",
    "requiresSpark": false,
    "isCommunity": true
},
{
    "id": "RStudio",
    "label": "RStudio (R 4.1.0, Bioconductor 3.13.0, Python 3.8.5)",
    "version": "3.13.1",
    "updated": "2021-06-08",
    "packages": "https://storage.googleapis.com/terra-docker-image-documentation/placeholder.json",
    "image": "us.gcr.io/anvil-gcr-public/anvil-rstudio-bioconductor:3.13.1",
    "requiresSpark": false,
    "isRStudio": true
}]
